<?xml version="1.0" encoding="UTF-8"?><SLA Version="1.0"><TxList><Tx>open_site</Tx><Tx>vuser_end_Transaction</Tx><Tx>payment</Tx><Tx>login</Tx><Tx>profile_fill</Tx><Tx>UC3_ChooseFlight</Tx><Tx>choose_ticket</Tx><Tx>UC2_LoginLogout</Tx><Tx>UC7_Sign_Up</Tx><Tx>choose_time_of_flight</Tx><Tx>after_reg</Tx><Tx>vuser_init_Transaction</Tx><Tx>UC6_Del_Booking</Tx><Tx>UC5_Itinerary</Tx><Tx>search_flights_button</Tx><Tx>logout</Tx><Tx>UC4_Buying</Tx><Tx>delete_booking</Tx><Tx>sign_up_button</Tx><Tx>Action_Transaction</Tx><Tx>itinerary</Tx></TxList><SLARules><TrackingPeriodType>Default</TrackingPeriodType><TrackingPeriodValue></TrackingPeriodValue><TrackingPeriodTimeScale></TrackingPeriodTimeScale></SLARules></SLA>